fourier_forecast/__init__.py
fourier_forecast/fourier_forecast.py
fourier_forecast/plot.py
fourier_forecast-0.0.4.dist-info/METADATA
fourier_forecast-0.0.4.dist-info/WHEEL
fourier_forecast-0.0.4.dist-info/top_level.txt
fourier_forecast-0.0.4.dist-info/RECORD
