Metadata-Version: 2.1
Name: fourier_forecast
Version: 0.0.4
Summary: Time-series forecasting with Fourier series
Home-page: https://github.com/jcatankard/fourier_forecast
Author: Josh Tankard
Requires-Dist: numpy
Requires-Dist: plotly
